odoo/addons/purchase_order_duplicate_check/README.rst
odoo/addons/purchase_order_duplicate_check/__init__.py
odoo/addons/purchase_order_duplicate_check/__manifest__.py
odoo/addons/purchase_order_duplicate_check/i18n/it.po
odoo/addons/purchase_order_duplicate_check/i18n/purchase_order_duplicate_check.pot
odoo/addons/purchase_order_duplicate_check/models/__init__.py
odoo/addons/purchase_order_duplicate_check/models/purchase_order.py
odoo/addons/purchase_order_duplicate_check/models/purchase_order_line.py
odoo/addons/purchase_order_duplicate_check/models/res_config_settings.py
odoo/addons/purchase_order_duplicate_check/readme/CONFIGURE.rst
odoo/addons/purchase_order_duplicate_check/readme/CONTEXT.rst
odoo/addons/purchase_order_duplicate_check/readme/CONTRIBUTORS.rst
odoo/addons/purchase_order_duplicate_check/readme/DESCRIPTION.rst
odoo/addons/purchase_order_duplicate_check/readme/USAGE.rst
odoo/addons/purchase_order_duplicate_check/static/description/icon.png
odoo/addons/purchase_order_duplicate_check/static/description/index.html
odoo/addons/purchase_order_duplicate_check/tests/__init__.py
odoo/addons/purchase_order_duplicate_check/tests/test_purchase_order.py
odoo/addons/purchase_order_duplicate_check/views/purchase_order_views.xml
odoo/addons/purchase_order_duplicate_check/views/res_config_settings_views.xml
odoo/addons/purchase_order_duplicate_check/wizard/__init__.py
odoo/addons/purchase_order_duplicate_check/wizard/confirmation_wizard.py
odoo/addons/purchase_order_duplicate_check/wizard/confirmation_wizard_views.xml
odoo_addon_purchase_order_duplicate_check-16.0.1.0.0.4.dist-info/METADATA
odoo_addon_purchase_order_duplicate_check-16.0.1.0.0.4.dist-info/WHEEL
odoo_addon_purchase_order_duplicate_check-16.0.1.0.0.4.dist-info/top_level.txt
odoo_addon_purchase_order_duplicate_check-16.0.1.0.0.4.dist-info/RECORD
