Metadata-Version: 2.1
Name: odoo-addon-purchase_order_duplicate_check
Version: 16.0.1.0.0.4
Summary: Prevents overordering in the Purchase app with a Confirmation Wizard, 'Pending Orders' field, and activity tracking for repeated orders.
Home-page: https://github.com/OCA/purchase-workflow
Author: Cetmix, Odoo Community Association (OCA)
Author-email: support@odoo-community.org
License: AGPL-3
Classifier: Programming Language :: Python
Classifier: Framework :: Odoo
Classifier: Framework :: Odoo :: 16.0
Classifier: License :: OSI Approved :: GNU Affero General Public License v3
Requires-Python: >=3.10
Requires-Dist: odoo-addon-confirmation-wizard<16.1dev,>=16.0dev
Requires-Dist: odoo<16.1dev,>=16.0a
